adpa/__init__.py
adpa/agents/__init__.py
adpa/agents/base.py
adpa/agents/manager.py
adpa/agents/moderator.py
adpa/agents/router.py
adpa/agents/specialized.py
adpa/agents/types.py
adpa/api/__init__.py
adpa/api/app.py
adpa/api/types.py
adpa/api/routes/__init__.py
adpa/api/routes/auth.py
adpa/api/routes/datasets.py
adpa/api/routes/queries.py
adpa/api/routes/users.py
adpa/cli/__init__.py
adpa/cli/agent.py
adpa/cli/database.py
adpa/cli/monitor.py
adpa/cli/text2sql.py
adpa/core/__init__.py
adpa/core/events.py
adpa/core/exceptions.py
adpa/core/framework.py
adpa/core/manager.py
adpa/core/models.py
adpa/core/processor.py
adpa/core/state.py
adpa/core/types.py
adpa/core/utils.py
adpa/core/workflow.py
adpa/core/action/__init__.py
adpa/core/attention/__init__.py
adpa/core/config/__init__.py
adpa/core/config/env.py
adpa/core/config/logging.py
adpa/core/config/settings.py
adpa/core/desire/__init__.py
adpa/core/exceptions/__init__.py
adpa/core/position/__init__.py
adpa/database/__init__.py
adpa/database/config.py
adpa/database/connection.py
adpa/database/manager.py
adpa/database/models.py
adpa/database/repository.py
adpa/database/session.py
adpa/database/utils.py
adpa/database/migrations/env.py
adpa/database/migrations/versions/001_initial.py
adpa/database/migrations/versions/002_merge_old_migrations.py
adpa/database/migrations/versions/003_python312_updates.py
adpa/llms/__init__.py
adpa/llms/base.py
adpa/llms/gemini/__init__.py
adpa/llms/gemini/client.py
adpa/llms/groq/__init__.py
adpa/llms/groq/client.py
adpa/llms/openai/__init__.py
adpa/llms/openai/client.py
adpa/monitoring/__init__.py
adpa/monitoring/alerts.py
adpa/monitoring/system.py
adpa/monitoring/types.py
adpa/security/__init__.py
adpa/security/middleware/__init__.py
adpa/security/middleware/csrf.py
adpa/security/sanitization/__init__.py
adpa/security/sanitization/sanitizer.py
adpa/sql/__init__.py
adpa/sql/generator.py
adpa/sql/middleware.py
adpa/sql/validation.py
adpa/templates/README.md
adpa/templates/html/base.html
adpa-0.1.6.dist-info/LICENSE
adpa-0.1.6.dist-info/METADATA
adpa-0.1.6.dist-info/WHEEL
adpa-0.1.6.dist-info/entry_points.txt
adpa-0.1.6.dist-info/top_level.txt
adpa-0.1.6.dist-info/RECORD
