Metadata-Version: 2.2
Name: adpa
Version: 0.1.6
Summary: Advanced Data Processing and Analytics Framework
Home-page: https://github.com/adpa/adpa
Author: ADPA Team
Author-email: ADPA Team <info@adpa.io>
Maintainer-email: ADPA Team <info@adpa.io>
License: MIT License
Project-URL: Homepage, https://github.com/adpa/adpa
Project-URL: Documentation, https://adpa.readthedocs.io/
Project-URL: Repository, https://github.com/adpa/adpa.git
Project-URL: Bug Tracker, https://github.com/adpa/adpa/issues
Project-URL: Release Notes, https://github.com/adpa/adpa/blob/main/CHANGELOG.md
Keywords: data processing,analytics,machine learning,artificial intelligence,data science,database,sql,async,api
Classifier: Development Status :: 4 - Beta
Classifier: Intended Audience :: Developers
Classifier: Topic :: Software Development :: Libraries :: Python Modules
Classifier: Topic :: Database :: Database Engines/Servers
Classifier: Topic :: Scientific/Engineering :: Artificial Intelligence
Classifier: License :: OSI Approved :: MIT License
Classifier: Programming Language :: Python :: 3
Classifier: Programming Language :: Python :: 3.8
Classifier: Programming Language :: Python :: 3.9
Classifier: Programming Language :: Python :: 3.10
Classifier: Programming Language :: Python :: 3.11
Classifier: Operating System :: OS Independent
Classifier: Framework :: AsyncIO
Classifier: Framework :: Jupyter
Classifier: Framework :: FastAPI
Classifier: Typing :: Typed
Requires-Python: >=3.8
License-File: LICENSE
Requires-Dist: pydantic>=2.0.0
Requires-Dist: sqlalchemy>=2.0.0
Requires-Dist: fastapi>=0.100.0
Requires-Dist: uvicorn>=0.22.0
Requires-Dist: pandas>=2.0.0
Requires-Dist: numpy>=1.24.0
Requires-Dist: python-dotenv>=1.0.0
Requires-Dist: requests>=2.31.0
Requires-Dist: aiohttp>=3.8.0
Requires-Dist: asyncio>=3.4.3
Requires-Dist: typing-extensions>=4.7.0
Requires-Dist: click>=8.1.0
Requires-Dist: rich>=13.4.0
Requires-Dist: tqdm>=4.65.0
Requires-Dist: loguru>=0.7.0
Requires-Dist: prometheus-client>=0.17.0
Requires-Dist: opentelemetry-api>=1.19.0
Requires-Dist: opentelemetry-sdk>=1.19.0
Requires-Dist: cryptography>=41.0.0
Requires-Dist: pyjwt>=2.8.0
Requires-Dist: bcrypt>=4.0.0
Provides-Extra: docs
Requires-Dist: mkdocs>=1.5.0; extra == "docs"
Requires-Dist: mkdocs-material>=9.5.0; extra == "docs"
Requires-Dist: mkdocstrings>=0.24.0; extra == "docs"
Requires-Dist: mkdocstrings-python>=1.8.0; extra == "docs"
Requires-Dist: mkdocs-git-revision-date-plugin>=0.3.2; extra == "docs"
Dynamic: author
Dynamic: home-page
Dynamic: requires-python
